{
  "errors": [
    {
      "code": "<string>",
      "detail": "<string>"
    },
    {
      "code": "<string>",
      "detail": "<string>"
    }
  ],
  "data": {
    "id": "<string>",
    "product": "drewry-freight",
    "tickerSymbol": "<string>",
    "fullName": "<string>",
    "type": "forward",
    "assessmentFrequency": [
      {
        "weekday": "wednesday",
        "openingTime": "<string>",
        "closingTime": "<string>",
        "timezone": "GMT"
      },
      {
        "weekday": "thursday",
        "openingTime": "<string>",
        "closingTime": "<string>",
        "timezone": "GMT"
      }
    ],
    "contractAssumptions": {
      "vesselSizeInM3": -21804874,
      "duration": -12658909,
      "basin": "atlantic",
      "deliveryPeriod": "<string>",
      "currency": "USD",
      "uom": "usd/day",
      "contractSize": 28023563
    },
    "lastUpdatedAt": "1941-12-16T08:07:39.348Z",
    "latestPriceRelease": {
      "id": -96636725,
      "releaseDate": "1957-03-03"
    },
    "nextPriceRelease": {
      "id": -49969928,
      "releaseDate": "1956-02-02"
    },
    "firstPriceRelease": {
      "id": 51029719,
      "releaseDate": "1959-06-28"
    }
  }
}
